quickdb/__init__.py
quickdb/main.py
quickDatabase-0.0.5.dist-info/LICENSE
quickDatabase-0.0.5.dist-info/METADATA
quickDatabase-0.0.5.dist-info/WHEEL
quickDatabase-0.0.5.dist-info/entry_points.txt
quickDatabase-0.0.5.dist-info/top_level.txt
quickDatabase-0.0.5.dist-info/RECORD
