Metadata-Version: 2.1
Name: quickDatabase
Version: 0.0.5
Summary: Simple python database
Home-page: https://github.com/py-contributors/python-db
Author: Deepak Raj
Author-email: deepak008@live.com
Keywords: python database
Classifier: Development Status :: 3 - Alpha
Classifier: Programming Language :: Python :: 3
Classifier: License :: OSI Approved :: MIT License
Classifier: Operating System :: OS Independent
Classifier: Intended Audience :: End Users/Desktop
Classifier: Intended Audience :: Developers
Requires-Python: >=3.4
License-File: LICENSE
